py_etp_client/__init__.py
py_etp_client/auth.py
py_etp_client/docs.py
py_etp_client/etp_requests.py
py_etp_client/etpclient.py
py_etp_client/etpconfig.py
py_etp_client/etpscript.py
py_etp_client/etpsimpleclient.py
py_etp_client/serverprotocols.py
py_etp_client/storage_interface.py
py_etp_client/utils.py
py_etp_client-1.1.1.dist-info/LICENSE
py_etp_client-1.1.1.dist-info/METADATA
py_etp_client-1.1.1.dist-info/WHEEL
py_etp_client-1.1.1.dist-info/RECORD
