Metadata-Version: 2.3
Name: py-etp-client
Version: 1.1.1
Summary: A python client to interact with the ETP server in with a websocket connection
License: Apache-2.0
Author: Valentin Gauthier
Author-email: valentin.gauthier@geosiris.com
Requires-Python: >=3.9,<4.0
Classifier: License :: OSI Approved :: Apache Software License
Classifier: Programming Language :: Python :: 3
Classifier: Programming Language :: Python :: 3.9
Classifier: Programming Language :: Python :: 3.10
Classifier: Programming Language :: Python :: 3.11
Classifier: Programming Language :: Python :: 3.12
Classifier: Programming Language :: Python :: 3.13
Provides-Extra: aws
Provides-Extra: azure
Provides-Extra: google
Provides-Extra: hdf5
Requires-Dist: boto3 (>=1.40.45,<2.0.0) ; extra == "aws"
Requires-Dist: botocore (>=1.40.45,<2.0.0) ; extra == "aws"
Requires-Dist: dotenv (>=0.9.9,<0.10.0)
Requires-Dist: energyml-prodml2-2 (>=1.12.0,<2.0.0)
Requires-Dist: energyml-resqml2-0-1 (>=1.12.0,<2.0.0)
Requires-Dist: energyml-resqml2-2 (>=1.12.0,<2.0.0)
Requires-Dist: energyml-utils (>=1.9.2,<2.0.0)
Requires-Dist: energyml-witsml2-0 (>=1.12.0,<2.0.0)
Requires-Dist: energyml-witsml2-1 (>=1.12.0,<2.0.0)
Requires-Dist: etpproto (>=1.0.7,<2.0.0)
Requires-Dist: google-auth (>=2.28.0,<3.0.0) ; extra == "google"
Requires-Dist: google-auth-oauthlib (>=1.0.0,<2.0.0) ; extra == "google"
Requires-Dist: h5py (>=3.10.0,<4.0.0) ; extra == "hdf5"
Requires-Dist: msal (>=1.24.0,<2.0.0) ; extra == "azure"
Requires-Dist: numpy (>=1.26.0,<2.0.0)
Requires-Dist: pyjwt (>=2.8.0,<3.0.0) ; extra == "azure"
Requires-Dist: pyyaml (>=6.0.2,<7.0.0)
Requires-Dist: requests (>=2.31.0,<3.0.0)
Requires-Dist: websocket-client (>=1.0.0,<2.0.0)
